describe_datasets.py
utils.py
bgd/__init__.py
bgd/utils.py
bgd/loaders/__init__.py
bgd/loaders/loaders.py
bgd/real/__init__.py
bgd/real/cora_dataset.py
bgd/real/example_dataset.py
bgd/real/facebook_dataset.py
bgd/real/from_ogb_dataset.py
bgd/real/from_tu_dataset.py
bgd/real/livejournal_dataset.py
bgd/real/neural_dataset.py
bgd/real/pennsylvania_road_dataset.py
bgd/real/reddit_dataset.py
bgd/real/twitch_ego_dataset.py
bgd/synthetic/__init__.py
bgd/synthetic/community_dataset.py
bgd/synthetic/lattice_dataset.py
bgd/synthetic/random_dataset.py
bgd/synthetic/tree_dataset.py
datasets/__init__.py
datasets/loaders/__init__.py
datasets/loaders/loaders.py
datasets/real/__init__.py
datasets/real/cora_dataset.py
datasets/real/ego_dataset.py
datasets/real/example_dataset.py
datasets/real/facebook_dataset.py
datasets/real/from_ogb_dataset.py
datasets/real/from_tu_dataset.py
datasets/real/neural_dataset.py
datasets/real/reddit_dataset.py
datasets/real/road_dataset.py
datasets/synthetic/__init__.py
datasets/synthetic/community_dataset.py
datasets/synthetic/lattice_dataset.py
datasets/synthetic/random_dataset.py
datasets/synthetic/tree_dataset.py
top/__init__.py
top/top.py
top/top_dataset.py
unsupervised/__init__.py
unsupervised/utils.py
unsupervised/convs/__init__.py
unsupervised/convs/gine_conv.py
unsupervised/convs/inits.py
unsupervised/convs/wgin_conv.py
unsupervised/encoder/__init__.py
unsupervised/encoder/encoder.py
unsupervised/learning/__init__.py
unsupervised/learning/ginfomax.py
unsupervised/learning/ginfominmax.py
unsupervised/learning/gsimclr.py
big_graph_dataset-0.0.8.post5.dist-info/METADATA
big_graph_dataset-0.0.8.post5.dist-info/WHEEL
big_graph_dataset-0.0.8.post5.dist-info/top_level.txt
big_graph_dataset-0.0.8.post5.dist-info/RECORD
