Metadata-Version: 2.1
Name: big-graph-dataset
Version: 0.0.8.post5
Summary: A collection of graph datasets in torch_geometric format.
Home-page: https://github.com/neutralpronoun/big-graph-dataset
Author: Alex O. Davies
Author-email: alexander.davies@bristol.ac.uk
Classifier: Programming Language :: Python :: 3
Classifier: License :: OSI Approved :: MIT License
Classifier: Operating System :: OS Independent
Requires-Python: >=3.8
Requires-Dist: aiohappyeyeballs==2.4.0
Requires-Dist: aiohttp==3.10.5
Requires-Dist: aiosignal==1.3.1
Requires-Dist: alabaster==1.0.0
Requires-Dist: attrs==24.2.0
Requires-Dist: babel==2.16.0
Requires-Dist: beautifulsoup4==4.12.3
Requires-Dist: bleach==6.1.0
Requires-Dist: Brotli==1.1.0
Requires-Dist: build==1.2.2
Requires-Dist: certifi==2024.8.30
Requires-Dist: charset-normalizer==3.3.2
Requires-Dist: click==8.1.7
Requires-Dist: cmake==3.30.2
Requires-Dist: contourpy==1.3.0
Requires-Dist: cycler==0.12.1
Requires-Dist: Cython==3.0.11
Requires-Dist: decorator==5.1.1
Requires-Dist: defusedxml==0.7.1
Requires-Dist: docutils==0.20.1
Requires-Dist: fastjsonschema==2.20.0
Requires-Dist: filelock==3.16.0
Requires-Dist: fonttools==4.53.1
Requires-Dist: frozenlist==1.4.1
Requires-Dist: fsspec==2024.3.1
Requires-Dist: gmpy2==2.2.1
Requires-Dist: idna==3.8
Requires-Dist: imagesize==1.4.1
Requires-Dist: Jinja2==3.1.4
Requires-Dist: joblib==1.4.2
Requires-Dist: jsonpickle==3.2.2
Requires-Dist: jsonschema==4.23.0
Requires-Dist: jsonschema-specifications==2023.12.1
Requires-Dist: jupyter-client==8.6.2
Requires-Dist: jupyter-core==5.7.2
Requires-Dist: jupyterlab-pygments==0.3.0
Requires-Dist: kiwisolver==1.4.7
Requires-Dist: latexcodec==3.0.0
Requires-Dist: littleballoffur==2.3.1
Requires-Dist: littleutils==0.2.4
Requires-Dist: llvmlite==0.43.0
Requires-Dist: MarkupSafe==2.1.5
Requires-Dist: matplotlib==3.9.2
Requires-Dist: mistune==3.0.2
Requires-Dist: mpmath==1.3.0
Requires-Dist: multidict==6.0.5
Requires-Dist: nbclient==0.10.0
Requires-Dist: nbconvert==7.16.4
Requires-Dist: nbformat==5.10.4
Requires-Dist: nbsphinx==0.9.5
Requires-Dist: networkit==11.0
Requires-Dist: networkx==3.1
Requires-Dist: numba==0.60.0
Requires-Dist: numpy==2.1.1
Requires-Dist: ogb==1.3.6
Requires-Dist: outdated==0.2.2
Requires-Dist: packaging==24.1
Requires-Dist: pandas==1.5.3
Requires-Dist: pandocfilters==1.5.1
Requires-Dist: pillow==10.4.0
Requires-Dist: pip-tools==7.4.1
Requires-Dist: platformdirs==4.2.2
Requires-Dist: psutil==6.0.0
Requires-Dist: pybtex==0.24.0
Requires-Dist: pybtex-docutils==1.0.3
Requires-Dist: Pygments==2.18.0
Requires-Dist: pynndescent==0.5.13
Requires-Dist: pyparsing==3.1.4
Requires-Dist: pyproject-hooks==1.1.0
Requires-Dist: PySocks==1.7.1
Requires-Dist: python-dateutil==2.9.0.post0
Requires-Dist: python-louvain==0.16
Requires-Dist: pytz==2024.1
Requires-Dist: PyYAML==6.0.2
Requires-Dist: pyzmq==26.2.0
Requires-Dist: referencing==0.35.1
Requires-Dist: requests==2.32.3
Requires-Dist: rpds-py==0.20.0
Requires-Dist: scikit-learn==1.5.1
Requires-Dist: scipy==1.14.1
Requires-Dist: six==1.16.0
Requires-Dist: snowballstemmer==2.2.0
Requires-Dist: soupsieve==2.6
Requires-Dist: Sphinx==8.0.2
Requires-Dist: sphinx-autodoc-typehints==2.2.3
Requires-Dist: sphinx-readme==1.2.1
Requires-Dist: sphinx-rtd-theme==2.0.0
Requires-Dist: sphinxcontrib-applehelp==2.0.0
Requires-Dist: sphinxcontrib-bibtex==2.6.2
Requires-Dist: sphinxcontrib-devhelp==2.0.0
Requires-Dist: sphinxcontrib-htmlhelp==2.1.0
Requires-Dist: sphinxcontrib-jquery==4.1
Requires-Dist: sphinxcontrib-jsmath==1.0.1
Requires-Dist: sphinxcontrib-qthelp==2.0.0
Requires-Dist: sphinxcontrib-serializinghtml==2.0.0
Requires-Dist: sympy==1.13.2
Requires-Dist: threadpoolctl==3.5.0
Requires-Dist: tinycss2==1.3.0
Requires-Dist: torch==2.4.0
Requires-Dist: torch-cluster==1.6.3
Requires-Dist: torch-geometric==2.5.3
Requires-Dist: torch-scatter==2.1.2
Requires-Dist: torch-sparse==0.6.18
Requires-Dist: torch-spline-conv==1.2.2
Requires-Dist: torchaudio==2.4.0
Requires-Dist: torchvision==0.19.0
Requires-Dist: tornado==6.4.1
Requires-Dist: tqdm==4.66.5
Requires-Dist: traitlets==5.14.3
Requires-Dist: typing-extensions==4.12.2
Requires-Dist: tzdata==2024.1
Requires-Dist: umap-learn==0.5.6
Requires-Dist: unicodedata2==15.1.0
Requires-Dist: urllib3==2.2.2
Requires-Dist: webencodings==0.5.1
Requires-Dist: wget==3.2
Requires-Dist: yarl==1.9.4
